<?xml version="1.0" encoding="ISO-8859-1" ?>
<server_status>
<daemon_status>
  <daemon>
        <host>yafu.myfirewall.org</host>
        <command>Download server</command>
        <status>running</status>
    </daemon>
  <daemon>
        <host>yafu.myfirewall.org</host>
        <command>Upload server</command>
        <status>running</status>
    </daemon>
  <daemon>
        <host>debian</host>
        <command>Scheduler</command>
        <status>running</status>
    </daemon>
  <daemon>
        <host>debian</host>
        <command>
        feeder</command>
        <status>running</status>
    </daemon>
  <daemon>
        <host>debian</host>
        <command>
        transitioner</command>
        <status>running</status>
    </daemon>
  <daemon>
        <host>debian</host>
        <command>
        file_deleter</command>
        <status>running</status>
    </daemon>
  <daemon>
        <host>debian</host>
        <command>   	sample_assimilator (example_app	)</command>
        <status>running</status>
    </daemon>
  <daemon>
        <host>debian</host>
        <command>   	sample_trivial_validator (yafu	)</command>
        <status>running</status>
    </daemon>
  <daemon>
        <host>debian</host>
        <command>   	sample_assimilator (yafu	)</command>
        <status>running</status>
    </daemon>
  <daemon>
        <host>debian</host>
        <command>   	sample_trivial_validator (yafu-low	)</command>
        <status>running</status>
    </daemon>
  <daemon>
        <host>debian</host>
        <command>   	sample_assimilator (yafu-low	)</command>
        <status>running</status>
    </daemon>
  <daemon>
        <host>debian</host>
        <command>   	sample_trivial_validator (yafu-4t	)</command>
        <status>running</status>
    </daemon>
  <daemon>
        <host>debian</host>
        <command>   	sample_assimilator (yafu-4t	)</command>
        <status>running</status>
    </daemon>
  <daemon>
        <host>debian</host>
        <command>   	sample_trivial_validator (yafu-8t	)</command>
        <status>running</status>
    </daemon>
  <daemon>
        <host>debian</host>
        <command>   	sample_assimilator (yafu-8t	)</command>
        <status>running</status>
    </daemon>
  <daemon>
        <host>debian</host>
        <command>   	sample_trivial_validator (yafu-16t	)</command>
        <status>running</status>
    </daemon>
  <daemon>
        <host>debian</host>
        <command>   	sample_assimilator (yafu-16t	)</command>
        <status>running</status>
    </daemon>
  <daemon>
        <host>debian</host>
        <command>   	sample_trivial_validator (benchmark	)</command>
        <status>running</status>
    </daemon>
  <daemon>
        <host>debian</host>
        <command>   	sample_assimilator (benchmark	)</command>
        <status>running</status>
    </daemon>
  <daemon>
        <host>debian</host>
        <command>   	db_purge</command>
        <status>running</status>
    </daemon>
</daemon_status>
<database_file_states>
   <results_ready_to_send>711</results_ready_to_send>
   <results_in_progress>585</results_in_progress>
   <workunits_waiting_for_validation>0</workunits_waiting_for_validation>
   <workunits_waiting_for_assimilation>0</workunits_waiting_for_assimilation>
   <workunits_waiting_for_deletion>0</workunits_waiting_for_deletion>
   <results_waiting_for_deletion>0</results_waiting_for_deletion>
   <transitioner_backlog_hours>0</transitioner_backlog_hours>
   <users_with_recent_credit>275</users_with_recent_credit>
   <users_with_credit>1502</users_with_credit>
   <users_registered_in_past_24_hours>2</users_registered_in_past_24_hours>
   <hosts_with_recent_credit>994</hosts_with_recent_credit>
   <hosts_with_credit>8266</hosts_with_credit>
   <hosts_registered_in_past_24_hours>3</hosts_registered_in_past_24_hours>
   <current_floating_point_speed>16258.110501851</current_floating_point_speed>
<tasks_by_app>
<app>
   <id>3</id>
   <name>yafu</name>
   <unsent>4</unsent>
   <in_progress>236</in_progress>
   <avg_runtime>1.9800</avg_runtime>
   <min_runtime>0.0100</min_runtime>
   <max_runtime>113.3500</max_runtime>
   <users>28</users>
</app>
<app>
   <id>9</id>
   <name>yafu-low</name>
   <unsent>9</unsent>
   <in_progress>103</in_progress>
   <avg_runtime>0.6800</avg_runtime>
   <min_runtime>0.0100</min_runtime>
   <max_runtime>20.5000</max_runtime>
   <users>37</users>
</app>
<app>
   <id>10</id>
   <name>yafu-4t</name>
   <unsent>668</unsent>
   <in_progress>167</in_progress>
   <avg_runtime>4.1200</avg_runtime>
   <min_runtime>0.0100</min_runtime>
   <max_runtime>102.7800</max_runtime>
   <users>39</users>
</app>
<app>
   <id>11</id>
   <name>yafu-8t</name>
   <unsent>30</unsent>
   <in_progress>70</in_progress>
   <avg_runtime>6.1800</avg_runtime>
   <min_runtime>0.0100</min_runtime>
   <max_runtime>40.8900</max_runtime>
   <users>13</users>
</app>
<app>
   <id>12</id>
   <name>yafu-16t</name>
   <unsent>0</unsent>
   <in_progress>9</in_progress>
   <avg_runtime>6.8100</avg_runtime>
   <min_runtime>0.0100</min_runtime>
   <max_runtime>41.2200</max_runtime>
   <users>1</users>
</app>
</tasks_by_app>
</database_file_states>
</server_status>
